rer.solrpush-1.6.5-py3.10-nspkg.pth
rer/solrpush/__init__.py
rer/solrpush/configure.zcml
rer/solrpush/indexer.py
rer/solrpush/parser.py
rer/solrpush/permissions.zcml
rer/solrpush/setuphandlers.py
rer/solrpush/testing.py
rer/solrpush/upgrades.py
rer/solrpush/upgrades.zcml
rer/solrpush/vocabularies.py
rer/solrpush/adapters/__init__.py
rer/solrpush/adapters/configure.zcml
rer/solrpush/adapters/file.py
rer/solrpush/adapters/rss_feed.py
rer/solrpush/adapters/summary.py
rer/solrpush/browser/__init__.py
rer/solrpush/browser/configure.zcml
rer/solrpush/browser/controlpanel.py
rer/solrpush/browser/elevate_settings.py
rer/solrpush/browser/maintenance.py
rer/solrpush/browser/query_debug.py
rer/solrpush/browser/querybuilder.py
rer/solrpush/browser/scales.py
rer/solrpush/browser/overrides/plone.app.contenttypes.browser.templates.listing.pt
rer/solrpush/browser/static/.gitkeep
rer/solrpush/browser/static/package.json
rer/solrpush/browser/static/styles.css
rer/solrpush/browser/static/styles.css.map
rer/solrpush/browser/static/styles.scss
rer/solrpush/browser/static/yarn.lock
rer/solrpush/browser/static/dist/dev/main.js
rer/solrpush/browser/static/dist/dev/main.js.map
rer/solrpush/browser/static/dist/prod/main.js
rer/solrpush/browser/static/dist/prod/main.js.map
rer/solrpush/browser/static/javascripts/index.js
rer/solrpush/browser/static/javascripts/FacetsContainer/index.js
rer/solrpush/browser/static/javascripts/ProgressBar/index.js
rer/solrpush/browser/static/javascripts/ProgressBarContainer/index.js
rer/solrpush/browser/templates/controlpanel_layout.pt
rer/solrpush/browser/templates/query_debug.pt
rer/solrpush/browser/templates/reindex_solr.pt
rer/solrpush/interfaces/__init__.py
rer/solrpush/interfaces/adapter.py
rer/solrpush/interfaces/elevate.py
rer/solrpush/interfaces/layer.py
rer/solrpush/interfaces/queueprocessor.py
rer/solrpush/interfaces/settings.py
rer/solrpush/locales/README.rst
rer/solrpush/locales/__init__.py
rer/solrpush/locales/rer.solrpush.pot
rer.solrpush-1.6.5.dist-info/LICENSE.GPL
rer.solrpush-1.6.5.dist-info/LICENSE.rst
rer.solrpush-1.6.5.dist-info/METADATA
rer.solrpush-1.6.5.dist-info/WHEEL
rer.solrpush-1.6.5.dist-info/entry_points.txt
rer.solrpush-1.6.5.dist-info/namespace_packages.txt
rer.solrpush-1.6.5.dist-info/top_level.txt
rer.solrpush-1.6.5.dist-info/RECORD
