Metadata-Version: 2.1
Name: rer.solrpush
Version: 1.6.5
Summary: Prodotto per Regione Emilia-Romagna relativo all'indicizzazione dei contenuti con solr
Home-page: https://github.com/collective/rer.solrpush
Author: RedTurtle
Author-email: sviluppoplone@redturtle.it
License: GPL version 2
Project-URL: PyPI, https://pypi.python.org/pypi/rer.solrpush
Project-URL: Source, https://github.com/collective/rer.solrpush
Project-URL: Tracker, https://github.com/collective/rer.solrpush/issues
Keywords: Python Plone
Classifier: Environment :: Web Environment
Classifier: Development Status :: 5 - Production/Stable
Classifier: Framework :: Plone
Classifier: Framework :: Plone :: Addon
Classifier: Framework :: Plone :: 5.1
Classifier: Framework :: Plone :: 5.2
Classifier: Framework :: Plone :: 6.0
Classifier: Programming Language :: Python
Classifier: Programming Language :: Python :: 3.6
Classifier: Programming Language :: Python :: 3.7
Classifier: Programming Language :: Python :: 3.8
Classifier: Programming Language :: Python :: 3.9
Classifier: Operating System :: OS Independent
Classifier: License :: OSI Approved :: GNU General Public License v2 (GPLv2)
Requires-Python: >=3.7
License-File: LICENSE.GPL
License-File: LICENSE.rst
Requires-Dist: setuptools
Requires-Dist: collective.z3cform.jsonwidget
Requires-Dist: plone.api >=1.8.4
Requires-Dist: pysolr
Requires-Dist: plone.restapi >=8.13.0
Requires-Dist: z3c.jbot
Requires-Dist: ftfy ==4.4.3 ; python_version <= "2.7"
Provides-Extra: test
Requires-Dist: plone.app.testing ; extra == 'test'
Requires-Dist: plone.testing >=5.0.0 ; extra == 'test'
Requires-Dist: plone.app.contenttypes ; extra == 'test'
Requires-Dist: plone.app.robotframework[debug] ; extra == 'test'
Requires-Dist: collective.MockMailHost ; extra == 'test'
